<annotation>
	<folder>300px-manos-mostrando-frames</folder>
	<filename>M_G_Mostrando_Manos_146.jpg</filename>
	<path>/home/julian/Documentos/dugai/Dataset-Bib/Dataset-ma&#241;ana-difdistancia/300px-manos-mostrando-frames/300px-manos-mostrando-frame-000084.jpg</path>
	<source>
		<database>Unknown</database>
	</source>
	<size>
		<width>1920</width>
		<height>1080</height>
		<depth>3</depth>
	</size>
	<segmented>0</segmented>
	<object>
		<name>hand</name>
		<pose>Unspecified</pose>
		<truncated>0</truncated>
		<difficult>0</difficult>
		<bndbox>
			<xmin>1287</xmin>
			<ymin>495</ymin>
			<xmax>1509</xmax>
			<ymax>694</ymax>
		</bndbox>
	</object>
	<object>
		<name>hand</name>
		<pose>Unspecified</pose>
		<truncated>0</truncated>
		<difficult>0</difficult>
		<bndbox>
			<xmin>1553</xmin>
			<ymin>461</ymin>
			<xmax>1687</xmax>
			<ymax>655</ymax>
		</bndbox>
	</object>
</annotation>