<annotation>
	<folder>300px-trabajando-manosguantes-noche-frames</folder>
	<filename>N_G_Trabajando_Mano-Verde_11.jpg</filename>
	<path>/home/federico/Escritorio/Repo/dugai/Dataset-Bib/Dataset-noche-difdistancia/300px-trabajando-manosguantes-noche-frames/300px-trabajando-manosguantes-noche-frame-000599.jpg</path>
	<source>
		<database>Unknown</database>
	</source>
	<size>
		<width>1920</width>
		<height>1080</height>
		<depth>3</depth>
	</size>
	<segmented>0</segmented>
	<object>
		<name>hand</name>
		<pose>Unspecified</pose>
		<truncated>0</truncated>
		<difficult>0</difficult>
		<bndbox>
			<xmin>1226</xmin>
			<ymin>376</ymin>
			<xmax>1435</xmax>
			<ymax>568</ymax>
		</bndbox>
	</object>
	<object>
		<name>hand</name>
		<pose>Unspecified</pose>
		<truncated>0</truncated>
		<difficult>0</difficult>
		<bndbox>
			<xmin>572</xmin>
			<ymin>441</ymin>
			<xmax>835</xmax>
			<ymax>779</ymax>
		</bndbox>
	</object>
</annotation>